[{"ac_num":"129","srch_fr_e":5,"srch_which_got_e":1,"srch_fr_q":1,"srch_which_got_q":1,"booking":1,"done_ride":1,"avg_dist_pr_trip":0,"avg_fare":40,"earning":40,"dist":0,"srch_to_e_rate":0.2,"e_to_q_srch_rate":1,"q_accept_rate":1,"q_to_bkng_rate":1,"cnvr_rate":0.2},{"ac_num":"130","srch_fr_e":1},{"ac_num":"131","srch_fr_e":2},{"ac_num":"132","srch_fr_e":962,"srch_which_got_e":849,"srch_fr_q":453,"srch_which_got_q":347,"booking":347,"done_ride":250,"cancel_ride":97,"drvr_cancel":36,"rider_cancel":61,"avg_dist_pr_trip":3.4173,"avg_fare":67.492,"earning":16873,"dist":854.328,"srch_to_e_rate":0.8825,"e_to_q_srch_rate":0.5336,"q_accept_rate":0.766,"q_to_bkng_rate":1,"bkng_cancel_rate":0.2795,"cnvr_rate":0.2599},{"ac_num":"133","srch_fr_e":55,"srch_which_got_e":16,"srch_fr_q":11,"srch_which_got_q":5,"booking":5,"done_ride":3,"cancel_ride":2,"drvr_cancel":1,"rider_cancel":1,"avg_dist_pr_trip":6.441,"avg_fare":116.6667,"earning":350,"dist":19.323,"srch_to_e_rate":0.2909,"e_to_q_srch_rate":0.6875,"q_accept_rate":0.4545,"q_to_bkng_rate":1,"bkng_cancel_rate":0.4,"cnvr_rate":0.0545},{"ac_num":"134","srch_fr_e":5,"srch_which_got_e":4,"srch_fr_q":3,"srch_to_e_rate":0.8,"e_to_q_srch_rate":0.75},{"ac_num":"135","srch_fr_e":1},{"ac_num":"136","srch_fr_e":1},{"ac_num":"138","srch_fr_e":2},{"ac_num":"150","srch_fr_e":5156,"srch_which_got_e":5089,"srch_fr_q":3269,"srch_which_got_q":2390,"booking":2375,"ongng_ride":3,"done_ride":1544,"cancel_ride":830,"drvr_cancel":475,"rider_cancel":353,"avg_dist_pr_trip":9.4063,"avg_fare":160.956,"earning":248677,"dist":14532.712,"srch_to_e_rate":0.987,"e_to_q_srch_rate":0.6424,"q_accept_rate":0.7311,"q_to_bkng_rate":0.9937,"bkng_cancel_rate":0.3495,"cnvr_rate":0.2995},{"ac_num":"151","srch_fr_e":20678,"srch_which_got_e":20676,"srch_fr_q":15681,"srch_which_got_q":9378,"booking":9309,"ongng_ride":9,"done_ride":6071,"cancel_ride":3229,"drvr_cancel":2114,"rider_cancel":1100,"avg_dist_pr_trip":7.4996,"avg_fare":135.9225,"earning":826137,"dist":45582.569,"srch_to_e_rate":0.9999,"e_to_q_srch_rate":0.7584,"q_accept_rate":0.598,"q_to_bkng_rate":0.9926,"bkng_cancel_rate":0.3469,"cnvr_rate":0.2936},{"ac_num":"152","srch_fr_e":12497,"srch_which_got_e":12455,"srch_fr_q":8789,"srch_which_got_q":6820,"booking":6784,"ongng_ride":8,"done_ride":4538,"cancel_ride":2234,"drvr_cancel":1422,"rider_cancel":803,"avg_dist_pr_trip":8.3131,"avg_fare":145.3144,"earning":659582,"dist":37733.359,"srch_to_e_rate":0.9966,"e_to_q_srch_rate":0.7057,"q_accept_rate":0.776,"q_to_bkng_rate":0.9947,"bkng_cancel_rate":0.3293,"cnvr_rate":0.3631},{"ac_num":"153","srch_fr_e":5715,"srch_which_got_e":5655,"srch_fr_q":3546,"srch_which_got_q":2688,"booking":2677,"ongng_ride":3,"done_ride":1805,"cancel_ride":868,"drvr_cancel":527,"rider_cancel":337,"avg_dist_pr_trip":8.3554,"avg_fare":143.7983,"earning":259556,"dist":15081.496,"srch_to_e_rate":0.9895,"e_to_q_srch_rate":0.6271,"q_accept_rate":0.758,"q_to_bkng_rate":0.9959,"bkng_cancel_rate":0.3242,"cnvr_rate":0.3158},{"ac_num":"154","srch_fr_e":9085,"srch_which_got_e":9077,"srch_fr_q":5986,"srch_which_got_q":4975,"booking":4957,"ongng_ride":5,"done_ride":3306,"cancel_ride":1646,"drvr_cancel":1004,"rider_cancel":632,"avg_dist_pr_trip":7.2947,"avg_fare":128.971,"earning":426765,"dist":24138.161,"srch_to_e_rate":0.9991,"e_to_q_srch_rate":0.6595,"q_accept_rate":0.8311,"q_to_bkng_rate":0.9964,"bkng_cancel_rate":0.3321,"cnvr_rate":0.3639},{"ac_num":"155","srch_fr_e":4932,"srch_which_got_e":4929,"srch_fr_q":3236,"srch_which_got_q":2522,"booking":2509,"done_ride":1631,"cancel_ride":877,"drvr_cancel":463,"rider_cancel":405,"avg_dist_pr_trip":6.7288,"avg_fare":120.473,"earning":196612,"dist":10981.338,"srch_to_e_rate":0.9994,"e_to_q_srch_rate":0.6565,"q_accept_rate":0.7794,"q_to_bkng_rate":0.9948,"bkng_cancel_rate":0.3495,"cnvr_rate":0.3307},{"ac_num":"156","srch_fr_e":3045,"srch_which_got_e":3044,"srch_fr_q":1923,"srch_which_got_q":1740,"booking":1735,"ongng_ride":2,"done_ride":1210,"cancel_ride":522,"drvr_cancel":291,"rider_cancel":225,"avg_dist_pr_trip":6.3231,"avg_fare":114.3339,"earning":138344,"dist":7650.985,"srch_to_e_rate":0.9997,"e_to_q_srch_rate":0.6317,"q_accept_rate":0.9048,"q_to_bkng_rate":0.9971,"bkng_cancel_rate":0.3009,"cnvr_rate":0.3974},{"ac_num":"157","srch_fr_e":6035,"srch_which_got_e":6029,"srch_fr_q":4346,"srch_which_got_q":3746,"booking":3729,"ongng_ride":5,"done_ride":2629,"cancel_ride":1095,"drvr_cancel":632,"rider_cancel":460,"avg_dist_pr_trip":6.5948,"avg_fare":119.3928,"earning":314003,"dist":17344.441,"srch_to_e_rate":0.999,"e_to_q_srch_rate":0.7208,"q_accept_rate":0.8619,"q_to_bkng_rate":0.9955,"bkng_cancel_rate":0.2936,"cnvr_rate":0.4356},{"ac_num":"158","srch_fr_e":6178,"srch_which_got_e":6178,"srch_fr_q":4404,"srch_which_got_q":3699,"booking":3683,"ongng_ride":6,"done_ride":2596,"cancel_ride":1079,"drvr_cancel":662,"rider_cancel":410,"avg_dist_pr_trip":6.5791,"avg_fare":119.1537,"earning":309323,"dist":17079.215,"srch_to_e_rate":1,"e_to_q_srch_rate":0.7129,"q_accept_rate":0.8399,"q_to_bkng_rate":0.9957,"bkng_cancel_rate":0.293,"cnvr_rate":0.4202},{"ac_num":"159","srch_fr_e":5027,"srch_which_got_e":5027,"srch_fr_q":3973,"srch_which_got_q":2830,"booking":2819,"ongng_ride":10,"done_ride":1804,"cancel_ride":999,"drvr_cancel":626,"rider_cancel":369,"avg_dist_pr_trip":5.8384,"avg_fare":110.1812,"earning":198877,"dist":10538.239,"srch_to_e_rate":1,"e_to_q_srch_rate":0.7903,"q_accept_rate":0.7123,"q_to_bkng_rate":0.9961,"bkng_cancel_rate":0.3544,"cnvr_rate":0.3589},{"ac_num":"160","srch_fr_e":12198,"srch_which_got_e":12198,"srch_fr_q":9399,"srch_which_got_q":7406,"booking":7378,"ongng_ride":16,"done_ride":5066,"cancel_ride":2290,"drvr_cancel":1396,"rider_cancel":881,"avg_dist_pr_trip":5.9234,"avg_fare":110.1951,"earning":558469,"dist":30019.658,"srch_to_e_rate":1,"e_to_q_srch_rate":0.7705,"q_accept_rate":0.788,"q_to_bkng_rate":0.9962,"bkng_cancel_rate":0.3104,"cnvr_rate":0.4153},{"ac_num":"161","srch_fr_e":15436,"srch_which_got_e":15436,"srch_fr_q":12396,"srch_which_got_q":8376,"booking":8352,"ongng_ride":20,"done_ride":5566,"cancel_ride":2762,"drvr_cancel":1654,"rider_cancel":1096,"avg_dist_pr_trip":6.5132,"avg_fare":121.8961,"earning":678961,"dist":36278.642,"srch_to_e_rate":1,"e_to_q_srch_rate":0.8031,"q_accept_rate":0.6757,"q_to_bkng_rate":0.9971,"bkng_cancel_rate":0.3307,"cnvr_rate":0.3606},{"ac_num":"162","srch_fr_e":12827,"srch_which_got_e":12825,"srch_fr_q":10341,"srch_which_got_q":7148,"booking":7114,"ongng_ride":10,"done_ride":4053,"cancel_ride":3048,"drvr_cancel":1874,"rider_cancel":1159,"avg_dist_pr_trip":7.0291,"avg_fare":128.6994,"earning":521876,"dist":28502.845,"srch_to_e_rate":0.9998,"e_to_q_srch_rate":0.8063,"q_accept_rate":0.6912,"q_to_bkng_rate":0.9952,"bkng_cancel_rate":0.4285,"cnvr_rate":0.316},{"ac_num":"163","srch_fr_e":14032,"srch_which_got_e":14031,"srch_fr_q":11372,"srch_which_got_q":8243,"booking":8198,"ongng_ride":36,"done_ride":4964,"cancel_ride":3188,"drvr_cancel":1847,"rider_cancel":1330,"avg_dist_pr_trip":6.4999,"avg_fare":124.7487,"earning":619502,"dist":32278.588,"srch_to_e_rate":0.9999,"e_to_q_srch_rate":0.8105,"q_accept_rate":0.7249,"q_to_bkng_rate":0.9945,"bkng_cancel_rate":0.3889,"cnvr_rate":0.3538},{"ac_num":"164","srch_fr_e":7130,"srch_which_got_e":7107,"srch_fr_q":4824,"srch_which_got_q":4116,"booking":4102,"ongng_ride":6,"done_ride":2456,"cancel_ride":1637,"drvr_cancel":1011,"rider_cancel":619,"avg_dist_pr_trip":7.6778,"avg_fare":137.0948,"earning":336842,"dist":18864.437,"srch_to_e_rate":0.9968,"e_to_q_srch_rate":0.6788,"q_accept_rate":0.8532,"q_to_bkng_rate":0.9966,"bkng_cancel_rate":0.3991,"cnvr_rate":0.3445},{"ac_num":"165","srch_fr_e":2026,"srch_which_got_e":2026,"srch_fr_q":1351,"srch_which_got_q":1261,"booking":1251,"ongng_ride":2,"done_ride":912,"cancel_ride":336,"drvr_cancel":201,"rider_cancel":135,"avg_dist_pr_trip":6.1712,"avg_fare":111.253,"earning":101574,"dist":5634.331,"srch_to_e_rate":1,"e_to_q_srch_rate":0.6668,"q_accept_rate":0.9334,"q_to_bkng_rate":0.9921,"bkng_cancel_rate":0.2686,"cnvr_rate":0.4501},{"ac_num":"166","srch_fr_e":2693,"srch_which_got_e":2691,"srch_fr_q":1764,"srch_which_got_q":1613,"booking":1606,"done_ride":1137,"cancel_ride":469,"drvr_cancel":269,"rider_cancel":198,"avg_dist_pr_trip":6.7145,"avg_fare":119.6218,"earning":136010,"dist":7634.382,"srch_to_e_rate":0.9993,"e_to_q_srch_rate":0.6555,"q_accept_rate":0.9144,"q_to_bkng_rate":0.9957,"bkng_cancel_rate":0.292,"cnvr_rate":0.4222},{"ac_num":"167","srch_fr_e":3239,"srch_which_got_e":3237,"srch_fr_q":2067,"srch_which_got_q":1889,"booking":1882,"ongng_ride":4,"done_ride":1241,"cancel_ride":636,"drvr_cancel":370,"rider_cancel":262,"avg_dist_pr_trip":6.6457,"avg_fare":119.6382,"earning":148471,"dist":8247.288,"srch_to_e_rate":0.9994,"e_to_q_srch_rate":0.6386,"q_accept_rate":0.9139,"q_to_bkng_rate":0.9963,"bkng_cancel_rate":0.3379,"cnvr_rate":0.3831},{"ac_num":"168","srch_fr_e":1522,"srch_which_got_e":1520,"srch_fr_q":1062,"srch_which_got_q":877,"booking":876,"done_ride":507,"cancel_ride":367,"drvr_cancel":255,"rider_cancel":112,"avg_dist_pr_trip":6.6681,"avg_fare":118.334,"earning":60232,"dist":3394.066,"srch_to_e_rate":0.9987,"e_to_q_srch_rate":0.6987,"q_accept_rate":0.8258,"q_to_bkng_rate":0.9989,"bkng_cancel_rate":0.4189,"cnvr_rate":0.3331},{"ac_num":"169","srch_fr_e":6243,"srch_which_got_e":6241,"srch_fr_q":4551,"srch_which_got_q":3682,"booking":3666,"ongng_ride":4,"done_ride":2389,"cancel_ride":1270,"drvr_cancel":746,"rider_cancel":519,"avg_dist_pr_trip":6.2496,"avg_fare":114.2849,"earning":273141,"dist":14936.552,"srch_to_e_rate":0.9997,"e_to_q_srch_rate":0.7292,"q_accept_rate":0.8091,"q_to_bkng_rate":0.9957,"bkng_cancel_rate":0.3464,"cnvr_rate":0.3827},{"ac_num":"170","srch_fr_e":3631,"srch_which_got_e":3624,"srch_fr_q":2569,"srch_which_got_q":2355,"booking":2347,"ongng_ride":1,"done_ride":1681,"cancel_ride":665,"drvr_cancel":393,"rider_cancel":266,"avg_dist_pr_trip":5.8533,"avg_fare":106.2826,"earning":178661,"dist":9839.341,"srch_to_e_rate":0.9981,"e_to_q_srch_rate":0.7089,"q_accept_rate":0.9167,"q_to_bkng_rate":0.9966,"bkng_cancel_rate":0.2833,"cnvr_rate":0.463},{"ac_num":"171","srch_fr_e":5323,"srch_which_got_e":5322,"srch_fr_q":3746,"srch_which_got_q":3263,"booking":3251,"ongng_ride":2,"done_ride":2316,"cancel_ride":932,"drvr_cancel":563,"rider_cancel":365,"avg_dist_pr_trip":5.9916,"avg_fare":109.2485,"earning":253238,"dist":13888.449,"srch_to_e_rate":0.9998,"e_to_q_srch_rate":0.7039,"q_accept_rate":0.8711,"q_to_bkng_rate":0.9963,"bkng_cancel_rate":0.2867,"cnvr_rate":0.4351},{"ac_num":"172","srch_fr_e":20215,"srch_which_got_e":20215,"srch_fr_q":15800,"srch_which_got_q":12168,"booking":12090,"ongng_ride":38,"done_ride":7494,"cancel_ride":4545,"drvr_cancel":2607,"rider_cancel":1921,"avg_dist_pr_trip":6.2984,"avg_fare":120.1157,"earning":900868,"dist":47237.828,"srch_to_e_rate":1,"e_to_q_srch_rate":0.7816,"q_accept_rate":0.7701,"q_to_bkng_rate":0.9936,"bkng_cancel_rate":0.3759,"cnvr_rate":0.3707},{"ac_num":"173","srch_fr_e":8254,"srch_which_got_e":8254,"srch_fr_q":6086,"srch_which_got_q":5042,"booking":5020,"ongng_ride":10,"done_ride":3445,"cancel_ride":1563,"drvr_cancel":942,"rider_cancel":614,"avg_dist_pr_trip":5.879,"avg_fare":109.6791,"earning":378064,"dist":20264.994,"srch_to_e_rate":1,"e_to_q_srch_rate":0.7373,"q_accept_rate":0.8285,"q_to_bkng_rate":0.9956,"bkng_cancel_rate":0.3114,"cnvr_rate":0.4174},{"ac_num":"174","srch_fr_e":36504,"srch_which_got_e":36468,"srch_fr_q":28727,"srch_which_got_q":13696,"booking":13642,"ongng_ride":28,"done_ride":8295,"cancel_ride":5314,"drvr_cancel":3316,"rider_cancel":1979,"avg_dist_pr_trip":9.0843,"avg_fare":162.7075,"earning":1350147,"dist":75381.421,"srch_to_e_rate":0.999,"e_to_q_srch_rate":0.7877,"q_accept_rate":0.4768,"q_to_bkng_rate":0.9961,"bkng_cancel_rate":0.3895,"cnvr_rate":0.2272},{"ac_num":"175","srch_fr_e":14944,"srch_which_got_e":14940,"srch_fr_q":11241,"srch_which_got_q":8941,"booking":8897,"ongng_ride":24,"done_ride":5792,"cancel_ride":3078,"drvr_cancel":1827,"rider_cancel":1236,"avg_dist_pr_trip":6.7765,"avg_fare":124.2176,"earning":719717,"dist":39263.12,"srch_to_e_rate":0.9997,"e_to_q_srch_rate":0.7524,"q_accept_rate":0.7954,"q_to_bkng_rate":0.9951,"bkng_cancel_rate":0.346,"cnvr_rate":0.3876},{"ac_num":"176","srch_fr_e":14792,"srch_which_got_e":14708,"srch_fr_q":10397,"srch_which_got_q":7537,"booking":7505,"ongng_ride":7,"done_ride":4895,"cancel_ride":2604,"drvr_cancel":1623,"rider_cancel":971,"avg_dist_pr_trip":7.9712,"avg_fare":140.0507,"earning":685688,"dist":39026.753,"srch_to_e_rate":0.9943,"e_to_q_srch_rate":0.7069,"q_accept_rate":0.7249,"q_to_bkng_rate":0.9958,"bkng_cancel_rate":0.347,"cnvr_rate":0.3309},{"ac_num":"177","srch_fr_e":2943,"srch_which_got_e":2761,"srch_fr_q":1876,"srch_which_got_q":983,"booking":972,"done_ride":622,"cancel_ride":351,"drvr_cancel":209,"rider_cancel":139,"avg_dist_pr_trip":13.2258,"avg_fare":222.7878,"earning":138574,"dist":8226.455,"srch_to_e_rate":0.9382,"e_to_q_srch_rate":0.6795,"q_accept_rate":0.524,"q_to_bkng_rate":0.9888,"bkng_cancel_rate":0.3611,"cnvr_rate":0.2113},{"ac_num":"178","srch_fr_e":373,"srch_which_got_e":269,"srch_fr_q":162,"srch_which_got_q":62,"booking":61,"done_ride":36,"cancel_ride":25,"drvr_cancel":10,"rider_cancel":15,"avg_dist_pr_trip":15.3551,"avg_fare":252.8889,"earning":9104,"dist":552.785,"srch_to_e_rate":0.7212,"e_to_q_srch_rate":0.6022,"q_accept_rate":0.3827,"q_to_bkng_rate":0.9839,"bkng_cancel_rate":0.4098,"cnvr_rate":0.0965},{"ac_num":"179","srch_fr_e":184,"srch_which_got_e":94,"srch_fr_q":36,"srch_which_got_q":19,"booking":19,"done_ride":7,"cancel_ride":12,"drvr_cancel":4,"rider_cancel":8,"avg_dist_pr_trip":31.767,"avg_fare":494.5714,"earning":3462,"dist":222.369,"srch_to_e_rate":0.5109,"e_to_q_srch_rate":0.383,"q_accept_rate":0.5278,"q_to_bkng_rate":1,"bkng_cancel_rate":0.6316,"cnvr_rate":0.038},{"ac_num":"180","srch_fr_e":35,"srch_which_got_e":15,"srch_to_e_rate":0.4286},{"ac_num":"181","srch_fr_e":164,"srch_which_got_e":146,"srch_fr_q":80,"srch_which_got_q":43,"booking":43,"done_ride":26,"cancel_ride":17,"drvr_cancel":5,"rider_cancel":12,"avg_dist_pr_trip":19.9718,"avg_fare":315.3846,"earning":8200,"dist":519.267,"srch_to_e_rate":0.8902,"e_to_q_srch_rate":0.5479,"q_accept_rate":0.5375,"q_to_bkng_rate":1,"bkng_cancel_rate":0.3953,"cnvr_rate":0.1585},{"ac_num":"182","srch_fr_e":46,"srch_which_got_e":28,"srch_fr_q":13,"srch_which_got_q":6,"booking":6,"done_ride":3,"cancel_ride":3,"rider_cancel":3,"avg_dist_pr_trip":24.0193,"avg_fare":393.3333,"earning":1180,"dist":72.058,"srch_to_e_rate":0.6087,"e_to_q_srch_rate":0.4643,"q_accept_rate":0.4615,"q_to_bkng_rate":1,"bkng_cancel_rate":0.5,"cnvr_rate":0.0652},{"ac_num":"183","srch_fr_e":41,"srch_which_got_e":12,"srch_fr_q":8,"srch_which_got_q":4,"booking":4,"cancel_ride":4,"rider_cancel":4,"srch_to_e_rate":0.2927,"e_to_q_srch_rate":0.6667,"q_accept_rate":0.5,"q_to_bkng_rate":1,"bkng_cancel_rate":1},{"ac_num":"184","srch_fr_e":3},{"ac_num":"185","srch_fr_e":15,"srch_which_got_e":1,"srch_to_e_rate":0.0667},{"ac_num":"211","srch_fr_e":2},{"ac_num":"212","srch_fr_e":3},{"ac_num":"214","srch_fr_e":2},{"ac_num":"215","srch_fr_e":281,"srch_which_got_e":275,"srch_fr_q":170,"srch_which_got_q":141,"booking":141,"done_ride":101,"cancel_ride":40,"drvr_cancel":17,"rider_cancel":23,"avg_dist_pr_trip":6.7681,"avg_fare":112.6337,"earning":11376,"dist":683.574,"srch_to_e_rate":0.9786,"e_to_q_srch_rate":0.6182,"q_accept_rate":0.8294,"q_to_bkng_rate":1,"bkng_cancel_rate":0.2837,"cnvr_rate":0.3594},{"ac_num":"216","srch_fr_e":411,"srch_which_got_e":407,"srch_fr_q":258,"srch_which_got_q":247,"booking":245,"done_ride":184,"cancel_ride":61,"drvr_cancel":24,"rider_cancel":37,"avg_dist_pr_trip":4.7591,"avg_fare":84.2772,"earning":15507,"dist":875.669,"srch_to_e_rate":0.9903,"e_to_q_srch_rate":0.6339,"q_accept_rate":0.9574,"q_to_bkng_rate":0.9919,"bkng_cancel_rate":0.249,"cnvr_rate":0.4477},{"ac_num":"217","srch_fr_e":575,"srch_which_got_e":566,"srch_fr_q":354,"srch_which_got_q":350,"booking":350,"done_ride":227,"cancel_ride":124,"drvr_cancel":66,"rider_cancel":58,"avg_dist_pr_trip":4.7512,"avg_fare":84.1013,"earning":19091,"dist":1078.523,"srch_to_e_rate":0.9843,"e_to_q_srch_rate":0.6254,"q_accept_rate":0.9887,"q_to_bkng_rate":1,"bkng_cancel_rate":0.3543,"cnvr_rate":0.3948},{"ac_num":"218","srch_fr_e":217,"srch_which_got_e":213,"srch_fr_q":139,"srch_which_got_q":130,"booking":130,"done_ride":77,"cancel_ride":53,"drvr_cancel":23,"rider_cancel":30,"avg_dist_pr_trip":5.1358,"avg_fare":88.961,"earning":6850,"dist":395.457,"srch_to_e_rate":0.9816,"e_to_q_srch_rate":0.6526,"q_accept_rate":0.9353,"q_to_bkng_rate":1,"bkng_cancel_rate":0.4077,"cnvr_rate":0.3548},{"ac_num":"219","srch_fr_e":6,"srch_which_got_e":2,"srch_fr_q":1,"srch_to_e_rate":0.3333,"e_to_q_srch_rate":0.5},{"ac_num":"220","srch_fr_e":1},{"ac_num":"ca_0","srch_fr_e":318,"srch_which_got_e":47,"srch_fr_q":12,"srch_which_got_q":3,"booking":3,"cancel_ride":3,"rider_cancel":3,"srch_to_e_rate":0.1478,"e_to_q_srch_rate":0.2553,"q_accept_rate":0.25,"q_to_bkng_rate":1,"bkng_cancel_rate":1}]
